CHANGELOG.rst
MANIFEST.in
README.rst
REQS.DEVELOP.txt
REQS.txt
VERSION
setup.cfg
setup.py
Flask_Store.egg-info/PKG-INFO
Flask_Store.egg-info/SOURCES.txt
Flask_Store.egg-info/dependency_links.txt
Flask_Store.egg-info/not-zip-safe
Flask_Store.egg-info/requires.txt
Flask_Store.egg-info/top_level.txt
flask_store/__init__.py
flask_store/exceptions.py
flask_store/sqla.py
flask_store/utils.py
flask_store/providers/__init__.py
flask_store/providers/local.py
flask_store/providers/s3.py
flask_store/providers/temp.py