Metadata-Version: 1.1
Name: Flask-Store
Version: 0.0.4.2
Summary: Provides Django-Storages like file storage backends for Flask Applications.
Home-page: http://flask-store.soon.build
Author: Chris Reeves
Author-email: hello@chris.reeves.io
License: MIT
Keywords: Flask,Files,Storage
Platform: UNKNOWN
Classifier: Framework :: Flask
Classifier: Environment :: Web Environment
Classifier: Intended Audience :: Developers
Classifier: License :: OSI Approved :: MIT License
Classifier: Development Status :: 3 - Alpha
Classifier: Operating System :: OS Independent
Classifier: Programming Language :: Python
Classifier: Programming Language :: Python :: 2
Classifier: Programming Language :: Python :: 2.7
Classifier: Topic :: Software Development
Classifier: Topic :: Software Development :: Libraries :: Python Modules
Classifier: Topic :: Internet :: WWW/HTTP :: Dynamic Content
